[
  {
    "order": 1,
    "id": "kasigau-id",
    "slug": "kasigau",
    "title": "The Wildlife Works Kasigau Project",
    "shortTitle": "Kasigau",
    "mainPicture": "/images/projects/kasigau/catalogue.jpg",
    "standards": "VCS, CCB",
    "location": {
      "iso": "KEN",
      "name": "Kenya",
      "centroid": [
        -1.286389,
        36.817223
      ],
      "geometry": null
    },
    "impact": [
      "Community",
      "Governance",
      "Biodiversity",
      "Climate"
    ]
  },
  {
    "order": 2,
    "id": "mai-ndombe-id",
    "slug": "mai-ndombe",
    "title": "The Wildlife Works Mai Ndombe Project",
    "shortTitle": "Mai Ndombe",
    "mainPicture": "/images/projects/mai-ndombe/catalogue.jpg",
    "standards": "VCS, CCB",
    "location": {
      "iso": "COD",
      "name": "Democratic Republic of the Congo",
      "centroid": [
        -4.643601,
        26.362312
      ],
      "geometry": null
    },
    "impact": [
      "Community",
      "Governance",
      "Biodiversity",
      "Climate"
    ]
  },
  {
    "order": 3,
    "id": "keo-seima-id",
    "slug": "keo-seima",
    "title": "The Wildlife Conservation Society Keo Seima Project",
    "shortTitle": "Keo Seima",
    "mainPicture": "/images/projects/keo-seima/catalogue.jpg",
    "standards": "VCS, CCB",
    "location": {
      "iso": "KHM",
      "name": "Cambodia",
      "centroid": [
        11.562108,
        104.888535
      ],
      "geometry": null
    },
    "impact": [
      "Community",
      "Governance",
      "Biodiversity",
      "Climate"
    ]
  },
  {
    "order": 4,
    "id": "tumring-id",
    "slug": "tumring",
    "title": "Tumring",
    "shortTitle": "Tumring",
    "mainPicture": "/images/projects/tumring/catalogue.jpg",
    "standards": "VCS, CCB",
    "location": {
      "iso": "KHM",
      "name": "Cambodia",
      "centroid": [
        11.562108,
        104.888535
      ],
      "geometry": null
    },
    "impact": [
      "Community",
      "Governance",
      "Biodiversity",
      "Climate"
    ]
  },
  {
    "order": 5,
    "id": "southern-cardamom-id",
    "slug": "southern-cardamom-id",
    "title": "The Wildlife Alliance Southern Cardamom Project",
    "shortTitle": "Southern Cardamom",
    "mainPicture": "/images/projects/southern-cardamom/catalogue.jpg",
    "standards": "VCS, CCB",
    "location": {
      "iso": "KHM",
      "name": "Cambodia",
      "centroid": [
        11.562108,
        104.888535
      ],
      "geometry": null
    },
    "impact": [
      "Community",
      "Governance",
      "Biodiversity",
      "Climate"
    ]
  },
  {
    "order": 6,
    "id": "guinea-bissau-id",
    "slug": "guinea-bissau",
    "title": "Guinea Bissau Avoided Deforestation",
    "shortTitle": "Guinea Bissau",
    "mainPicture": "/images/projects/guinea-bissau/catalogue.jpg",
    "standards": "VCS",
    "location": {
      "iso": "GB",
      "name": "Guinea Bissau",
      "centroid": [
        25.276987,
        55.296249
      ],
      "geometry": null
    }
  }
]